add_scalebar/__init__.py
add_scalebar/__main__.py
add_scalebar/addScaleBarGUI.py
em_add_scalebar-0.1.0.dist-info/LICENSE.txt
em_add_scalebar-0.1.0.dist-info/METADATA
em_add_scalebar-0.1.0.dist-info/WHEEL
em_add_scalebar-0.1.0.dist-info/top_level.txt
em_add_scalebar-0.1.0.dist-info/RECORD
